inspector/__init__.py
inspector/server.py
inspector/static.py
sweagent/__init__.py
sweagent/agent/__init__.py
sweagent/agent/agents.py
sweagent/agent/commands.py
sweagent/agent/history_processors.py
sweagent/agent/models.py
sweagent/agent/parsing.py
sweagent/environment/__init__.py
sweagent/environment/swe_env.py
sweagent/environment/utils.py
sweagent-0.0.1.dist-info/LICENSE
sweagent-0.0.1.dist-info/METADATA
sweagent-0.0.1.dist-info/WHEEL
sweagent-0.0.1.dist-info/top_level.txt
sweagent-0.0.1.dist-info/RECORD
