Metadata-Version: 2.1
Name: sweagent
Version: 0.0.1
Summary: The official SWE-agent package - an open source Agent Computer Interface for running language models as software engineers
Home-page: https://swe-agent.com
Author: John Yang
Author-email: byjohnyang@gmail.com
Project-URL: Documentation, https://github.com/princeton-nlp/SWE-agent
Project-URL: Bug Reports, http://github.com/princeton-nlp/SWE-agent/issues
Project-URL: Source Code, http://github.com/princeton-nlp/SWE-agent
Project-URL: Website, https://sweagent.com
Keywords: nlp,agents,code
Classifier: Programming Language :: Python :: 3.9
Classifier: Programming Language :: Python :: 3 :: Only
Classifier: License :: OSI Approved :: MIT License
Classifier: Operating System :: OS Independent
Requires-Python: >=3.9
License-File: LICENSE
Requires-Dist: anthropic
Requires-Dist: config
Requires-Dist: datasets
Requires-Dist: docker
Requires-Dist: gnureadline
Requires-Dist: gymnasium
Requires-Dist: numpy
Requires-Dist: openai >=1.0
Requires-Dist: pandas
Requires-Dist: rich
Requires-Dist: ruamel.yaml
Requires-Dist: simple-parsing
Requires-Dist: swebench >=1.0.1
Requires-Dist: tenacity
Requires-Dist: togetherunidiff
